napari_segmentation_overlap_filter/__init__.py
napari_segmentation_overlap_filter/_widget.py
napari_segmentation_overlap_filter/functions.py
napari_segmentation_overlap_filter/napari.yaml
napari_segmentation_overlap_filter/_tests/__init__.py
napari_segmentation_overlap_filter/_tests/test_reader.py
napari_segmentation_overlap_filter/_tests/test_widget.py
napari_segmentation_overlap_filter/_tests/test_writer.py
napari_segmentation_overlap_filter-0.0.1.dist-info/LICENSE
napari_segmentation_overlap_filter-0.0.1.dist-info/METADATA
napari_segmentation_overlap_filter-0.0.1.dist-info/WHEEL
napari_segmentation_overlap_filter-0.0.1.dist-info/entry_points.txt
napari_segmentation_overlap_filter-0.0.1.dist-info/top_level.txt
napari_segmentation_overlap_filter-0.0.1.dist-info/RECORD
